rate/__init__.py
rate/__main__.py
rate/calculator/__init__.py
rate/calculator/calculator.py
rate/config.py
rate/gui/__init__.py
rate/gui/gui.py
rate/main.py
rate/match/__init__.py
rate/match/match.py
rate/players/__init__.py
rate/players/dwz_player.py
rate/players/ecf_player.py
rate/players/elo_player.py
rate/players/glicko1_player.py
rate/players/glicko2_player.py
rate/players/player.py
rate/players/player_factory.py
rate/players/players_container.py
rate/players/trueskill_player.py
rate/readers/__init__.py
rate/readers/csv_reader.py
rate/readers/json_reader.py
rate/readers/reader.py
rate/readers/reader_factory.py
rate/utils/__init__.py
rate/utils/result_handler.py
rate/writers/__init__.py
rate/writers/csv_writer.py
rate/writers/json_writer.py
rate/writers/writer.py
rate/writers/writer_factory.py
rate-0.1.6.dist-info/entry_points.txt
rate-0.1.6.dist-info/LICENSE
rate-0.1.6.dist-info/WHEEL
rate-0.1.6.dist-info/METADATA
rate-0.1.6.dist-info/RECORD
