Metadata-Version: 2.1
Name: rate
Version: 0.1.6
Summary: A simple CLI tool to rate matches in a file.
License: GPL-3.0
Keywords: rate,match,rating,elo,glicko,trueskill
Author: blankalmasry
Author-email: blankhussien@gmail.com
Requires-Python: >=3.5,<4.0
Classifier: License :: OSI Approved :: GNU General Public License v3 (GPLv3)
Classifier: Programming Language :: Python :: 3
Classifier: Programming Language :: Python :: 3.10
Classifier: Programming Language :: Python :: 3.5
Classifier: Programming Language :: Python :: 3.6
Classifier: Programming Language :: Python :: 3.7
Classifier: Programming Language :: Python :: 3.8
Classifier: Programming Language :: Python :: 3.9
Requires-Dist: PyInquirer (==1.0.3)
Requires-Dist: elote (>=0.1.0,<0.2.0)
Requires-Dist: glicko2 (==2.0.0)
Requires-Dist: tqdm (>=4.32,<5.0)
Requires-Dist: trueskill (>=0.4.5,<0.5.0)
